cinagu/__init__.py
cinagu/chess_detection.py
cinagu/game_integration.py
cinagu/shooting_detection.py
cinagu/tests/__init__.py
cinagu/tests/test_chess_detection.py
cinagu/tests/test_shooting_detection.py
cinagu-0.1.4.dist-info/METADATA
cinagu-0.1.4.dist-info/WHEEL
cinagu-0.1.4.dist-info/top_level.txt
cinagu-0.1.4.dist-info/RECORD
