Metadata-Version: 2.1
Name: cinagu
Version: 0.1.4
Summary: A Python package for detecting cheats and hacks in various games.
Home-page: https://github.com/James7688/cinagu
Author: Quy Anh Nguyen
Author-email: quyanh082013@gmail.com
Classifier: Programming Language :: Python :: 3
Classifier: License :: OSI Approved :: MIT License
Classifier: Operating System :: OS Independent
Requires-Python: >=3.6
Requires-Dist: chess
